cellregulondb/__init__.py
cellregulondb/cellregulon.py
cellregulondb-0.1.0.dist-info/LICENSE
cellregulondb-0.1.0.dist-info/WHEEL
cellregulondb-0.1.0.dist-info/METADATA
cellregulondb-0.1.0.dist-info/RECORD
